deqart/__init__.py
deqart/__main__.py
deqart/backend_connection.py
deqart/circuit_serialization.py
deqart/deqart_client.py
deqart/estimate_result.py
deqart/exceptions.py
deqart/http_adapter.py
deqart/job_result.py
deqart/version.py
deqart/api/__init__.py
deqart/api/jobs.py
deqart-0.0.11b2.dist-info/LICENSE
deqart-0.0.11b2.dist-info/METADATA
deqart-0.0.11b2.dist-info/WHEEL
deqart-0.0.11b2.dist-info/entry_points.txt
deqart-0.0.11b2.dist-info/top_level.txt
deqart-0.0.11b2.dist-info/RECORD
