Metadata-Version: 2.1
Name: deqart
Version: 0.0.11b2
Summary: Python SDK to Deqart platform
Author: BlueQubit
Author-email: hovnatan@bluequbit.io
License: Apache 2.0
Requires-Python: >=3.7
License-File: LICENSE
Requires-Dist: requests (~=2.28)
Requires-Dist: requests-toolbelt (~=0.10)
Requires-Dist: python-dateutil (~=2.8)
Requires-Dist: numpy (~=1.21)
Requires-Dist: packaging (~=21.3)
